phoskhemia/__init__.py
phoskhemia/data/__init__.py
phoskhemia/data/spectrum_handlers.py
phoskhemia/fitting/__init__.py
phoskhemia/fitting/global_fit.py
phoskhemia/fitting/initialization.py
phoskhemia/fitting/projections.py
phoskhemia/fitting/validation.py
phoskhemia/kinetics/__init__.py
phoskhemia/kinetics/base.py
phoskhemia/kinetics/models.py
phoskhemia/preprocessing/__init__.py
phoskhemia/preprocessing/corrections.py
phoskhemia/preprocessing/smoothing.py
phoskhemia/utils/__init__.py
phoskhemia/utils/printing_utils.py
phoskhemia/utils/typing.py
phoskhemia/visualization/__init__.py
phoskhemia/visualization/plotting.py
phoskhemia-0.1.4.dist-info/licenses/LICENSE
tests/__init__.py
tests/test_smooth_bench.py
tests/test_spectrum_handlers.py
phoskhemia-0.1.4.dist-info/METADATA
phoskhemia-0.1.4.dist-info/WHEEL
phoskhemia-0.1.4.dist-info/top_level.txt
phoskhemia-0.1.4.dist-info/RECORD
