Metadata-Version: 2.4
Name: phoskhemia
Version: 0.1.4
Summary: Library for the handling and analysis of chemical spectroscopic data.
Author: Cole Clark
License: MIT
Project-URL: Homepage, https://github.com/cclark012/phoskhemia
Requires-Python: >=3.13
License-File: LICENSE
Requires-Dist: numpy
Requires-Dist: scipy
Requires-Dist: matplotlib
Requires-Dist: polars
Requires-Dist: numba
Dynamic: license-file
